{"이미지 정보":{"이미지 식별자":795184,"이미지 높이":1200,"이미지 파일명":"36-(10)-t1964(3)-린느(대행,린넨단가라)7.4-07목선에서 얼굴컷-IMG_4826.jpg","이미지 너비":800},"데이터셋 정보":{"파일 생성일자":"2020-11-02 20:11:47","데이터셋 상세설명":{"렉트좌표":{"아우터":[{}],"하의":[{}],"원피스":[{"X좌표":386.516,"Y좌표":462.516,"가로":178,"세로":495}],"상의":[{}]},"폴리곤좌표":{"아우터":[{}],"하의":[{}],"원피스":[{"Y좌표9":764.016,"Y좌표22":553.016,"Y좌표21":507.016,"Y좌표20":473.016,"X좌표19":524.016,"X좌표18":534.016,"X좌표17":537.016,"X좌표16":566.016,"X좌표15":523.016,"X좌표14":496.016,"X좌표13":497.016,"X좌표12":492.016,"X좌표11":416.016,"Y좌표4":524.016,"X좌표10":406.016,"Y좌표3":482.016,"Y좌표2":463.016,"Y좌표1":554.016,"Y좌표8":696.016,"Y좌표7":628.016,"Y좌표6":598.016,"Y좌표5":572.016,"Y좌표15":942.016,"Y좌표14":944.016,"X좌표8":403.016,"Y좌표17":612.016,"X좌표9":411.016,"Y좌표16":938.016,"Y좌표11":957.016,"Y좌표10":854.016,"Y좌표13":808.016,"Y좌표12":959.016,"X좌표22":493.016,"X좌표2":404.016,"X좌표21":502.016,"X좌표3":387.016,"X좌표20":507.016,"X좌표1":492.016,"X좌표6":413.016,"Y좌표19":477.016,"X좌표7":396.016,"Y좌표18":534.016,"X좌표4":414.016,"X좌표5":423.016}],"상의":[{}]},"라벨링":{"스타일":[{"스타일":"컨트리","서브스타일":"스트리트"}],"아우터":[{}],"하의":[{}],"원피스":[{"기장":"발목","색상":"그레이","카테고리":"점프수트","소매기장":"민소매","소재":["우븐"],"프린트":["무지"],"넥라인":"브이넥","핏":"루즈"}],"상의":[{}]}},"파일 번호":795184,"파일 이름":"36-(10)-t1964(3)-린느(대행,린넨단가라)7.4-07목선에서 얼굴컷-IMG_4826.jpg"}}